insnail_ai_tools/README.md
insnail_ai_tools/__init__.py
insnail_ai_tools/achilles.py
insnail_ai_tools/apollo_client.py
insnail_ai_tools/ark_api.py
insnail_ai_tools/asr.py
insnail_ai_tools/canal.py
insnail_ai_tools/cli.py
insnail_ai_tools/config.py
insnail_ai_tools/decorator.py
insnail_ai_tools/efficient.py
insnail_ai_tools/email.py
insnail_ai_tools/httpx.py
insnail_ai_tools/mdb.py
insnail_ai_tools/meta.py
insnail_ai_tools/ossutils.py
insnail_ai_tools/server.py
insnail_ai_tools/sso.py
insnail_ai_tools/type_convert.py
insnail_ai_tools/elastic_search/__init__.py
insnail_ai_tools/elastic_search/aio_connection.py
insnail_ai_tools/elastic_search/analyzer.py
insnail_ai_tools/elastic_search/mixin.py
insnail_ai_tools/elastic_search/mongodb_plugin.py
insnail_ai_tools/elastic_search/documents/__init__.py
insnail_ai_tools/elastic_search/documents/call_center.py
insnail_ai_tools/elastic_search/documents/wecom_department.py
insnail_ai_tools/elastic_search/documents/wecom_event.py
insnail_ai_tools/elastic_search/documents/wecom_external_user.py
insnail_ai_tools/elastic_search/documents/wecom_group_chat.py
insnail_ai_tools/elastic_search/documents/wecom_group_message.py
insnail_ai_tools/elastic_search/documents/wecom_meeting_voice.py
insnail_ai_tools/elastic_search/documents/wecom_personal_message.py
insnail_ai_tools/elastic_search/documents/wecom_user.py
insnail_ai_tools/elastic_search/documents/wecom_user_relation.py
insnail_ai_tools/elastic_search/documents/ontology/__init__.py
insnail_ai_tools/elastic_search/documents/ontology/disease.py
insnail_ai_tools/extractor/__init__.py
insnail_ai_tools/extractor/file.py
insnail_ai_tools/extractor/image.py
insnail_ai_tools/extractor/voice.py
insnail_ai_tools/mongodb/__init__.py
insnail_ai_tools/mongodb/aio_connection.py
insnail_ai_tools/mongodb/mixin.py
insnail_ai_tools/mongodb/model/__init__.py
insnail_ai_tools/mongodb/model/call_center.py
insnail_ai_tools/mongodb/model/knowledge.py
insnail_ai_tools/mongodb/model/message_check_rule.py
insnail_ai_tools-0.0.84.dist-info/entry_points.txt
insnail_ai_tools-0.0.84.dist-info/LICENSE
insnail_ai_tools-0.0.84.dist-info/WHEEL
insnail_ai_tools-0.0.84.dist-info/METADATA
insnail_ai_tools-0.0.84.dist-info/RECORD
