Metadata-Version: 2.1
Name: insnail_ai_tools
Version: 0.0.84
Summary: Insnail Ai Tools
Home-page: https://github.com/pypa/insnail_ai_tools
License: UNKNOWN
Author: Insnail Ai Team
Author-email: libiao@ingbaobei.com
Requires-Python: >=3.6
Classifier: License :: OSI Approved :: MIT License
Requires-Dist: flit ==3.0.0 ; extra == "dev"
Requires-Dist: ipython ==7.18.1 ; extra == "dev"
Requires-Dist: jedi ==0.17.2 ; extra == "dev"
Requires-Dist: pre-commit ==2.9.3 ; extra == "dev"
Requires-Dist: black ==20.8b1 ; extra == "dev"
Requires-Dist: isort ==5.6.4 ; extra == "dev"
Requires-Dist: flake8 ==3.8.4 ; extra == "dev"
Requires-Dist: pytest ==6.2.1 ; extra == "dev"
Requires-Dist: pytest-cov ==2.10.1 ; extra == "dev"
Requires-Dist: pytest-asyncio ==0.14.0 ; extra == "dev"
Requires-Dist: django ==3.1.4 ; extra == "django"
Requires-Dist: gunicorn ==20.0.4 ; extra == "django"
Requires-Dist: elasticsearch-dsl ==7.3.0 ; extra == "es"
Requires-Dist: fastapi[all] ==0.62.0 ; extra == "fastapi"
Requires-Dist: starlette ==0.13.6 ; extra == "fastapi"
Requires-Dist: pydantic ==1.6.1 ; extra == "fastapi"
Requires-Dist: uvicorn ==0.11.8 ; extra == "fastapi"
Requires-Dist: flask ==1.1.2 ; extra == "flask"
Requires-Dist: flask-cors ==3.0.9 ; extra == "flask"
Requires-Dist: gunicorn ==20.0.4 ; extra == "flask"
Requires-Dist: motor ==2.3.1 ; extra == "mongo"
Requires-Dist: pymongo ==3.11.3 ; extra == "mongo"
Requires-Dist: mongoengine ==0.22.1 ; extra == "mongo"
Requires-Dist: asyncio ==3.4.3 ; extra == "mussy"
Requires-Dist: apollo-client ==0.9.2 ; extra == "mussy"
Requires-Dist: pyyaml ==5.3.1 ; extra == "mussy"
Requires-Dist: requests ==2.24.0 ; extra == "mussy"
Requires-Dist: fire ==0.3.1 ; extra == "mussy"
Requires-Dist: aiohttp ==3.7.3 ; extra == "mussy"
Requires-Dist: tqdm ==4.50.2 ; extra == "mussy"
Requires-Dist: oss2 ==2.13.0 ; extra == "oss"
Requires-Dist: redis ==3.5.3 ; extra == "sso"
Requires-Dist: python-jose ==3.2.0 ; extra == "sso"
Requires-Dist: tencentcloud-sdk-python ==3.0.341 ; extra == "tx"
Requires-Dist: wechatpy ==2.0.0a5 ; extra == "wechat"
Provides-Extra: dev
Provides-Extra: django
Provides-Extra: doc
Provides-Extra: es
Provides-Extra: fastapi
Provides-Extra: flask
Provides-Extra: mongo
Provides-Extra: mussy
Provides-Extra: oss
Provides-Extra: sso
Provides-Extra: tx
Provides-Extra: wechat
